{
  "productNo": {
    "value": "01-R0107-11-13-18"
  },
  "name": {
    "value": "新井関所＿１１"
  },
  "contractorName": {
    "value": "不二総合"
  },
  "constructionPeriod": {
    "value": ""
  },
  "registeredDate": {
    "value": "2019-08-01"
  },
  "measuredDate": {
    "value": "2019-07-10"
  },
  "sourceStatement": {
    "value": "出典：「静岡県ポイントクラウドデータベース」または「静岡県ＰＣＤＢ」"
  },
  "id": "shizuoka-pcd-01R0107111318",
  "type": "PointCloudDatabase",
  "location": {
    "type": "geo:json",
    "value": {
      "type": "Polygon",
      "coordinates": [
        [
          [
            137.5603854814,
            34.693994281837
          ],
          [
            137.56037350794,
            34.695053622067
          ],
          [
            137.56230880748,
            34.695068529127
          ],
          [
            137.56232075628,
            34.694009188311
          ],
          [
            137.5603854814,
            34.693994281837
          ]
        ]
      ]
    }
  },
  "description": {
    "value": "新井関所＿１１, 不二総合"
  },
  "source": {
    "type": "URL",
    "value": "https://pointcloud.pref.shizuoka.jp"
  },
  "lasUrls": {
    "value": [
      "https://pointcloud.pref.shizuoka.jp/lasmap/public/01R0107111318/01R0107111318-1.las"
    ]
  },
  "lasSizes": {
    "value": [
      "74MB"
    ]
  },
  "license": {
    "type": "URL",
    "value": "https://creativecommons.org/licenses/by/4.0/legalcode.ja"
  }
}