{
  "productNo": {
    "value": "30-I8399-01-11-11"
  },
  "name": {
    "value": "平成30年度路面変状調査((一)239号線_相良浜岡線)"
  },
  "contractorName": {
    "value": "ニチレキ(株)静岡支店"
  },
  "constructionPeriod": {
    "value": ""
  },
  "registeredDate": {
    "value": "2019-10-15"
  },
  "measuredDate": {
    "value": "2019-03-31"
  },
  "sourceStatement": {
    "value": "出典：「静岡県ポイントクラウドデータベース」または「静岡県ＰＣＤＢ」"
  },
  "id": "shizuoka-pcd-30I8399011111",
  "type": "PointCloudDatabase",
  "location": {
    "type": "geo:json",
    "value": {
      "type": "Polygon",
      "coordinates": [
        [
          [
            138.13337690477,
            34.647286498513
          ],
          [
            138.1333719346,
            34.648415537343
          ],
          [
            138.13628177567,
            34.648424251122
          ],
          [
            138.1362867064,
            34.647295211926
          ],
          [
            138.13337690477,
            34.647286498513
          ]
        ]
      ]
    }
  },
  "description": {
    "value": "平成30年度路面変状調査((一)239号線_相良浜岡線), ニチレキ(株)静岡支店"
  },
  "source": {
    "type": "URL",
    "value": "https://pointcloud.pref.shizuoka.jp"
  },
  "lasUrls": {
    "value": [
      "https://pointcloud.pref.shizuoka.jp/lasmap/public/30I8399011111/30I8399011111-1.las",
      "https://pointcloud.pref.shizuoka.jp/lasmap/public/30I8399011111/30I8399011111-2.las",
      "https://pointcloud.pref.shizuoka.jp/lasmap/public/30I8399011111/30I8399011111-3.las"
    ]
  },
  "lasSizes": {
    "value": [
      "200MB",
      "200MB",
      "78MB"
    ]
  },
  "license": {
    "type": "URL",
    "value": "https://creativecommons.org/licenses/by/4.0/legalcode.ja"
  }
}