{
  "productNo": {
    "value": "30-I8399-01-73-07"
  },
  "name": {
    "value": "平成30年度路面変状調査((一)403号線_磐田掛川線(下り))"
  },
  "contractorName": {
    "value": "ニチレキ(株)静岡支店"
  },
  "constructionPeriod": {
    "value": ""
  },
  "registeredDate": {
    "value": "2019-10-15"
  },
  "measuredDate": {
    "value": "2019-03-31"
  },
  "sourceStatement": {
    "value": "出典：「静岡県ポイントクラウドデータベース」または「静岡県ＰＣＤＢ」"
  },
  "id": "shizuoka-pcd-30I8399017307",
  "type": "PointCloudDatabase",
  "location": {
    "type": "geo:json",
    "value": {
      "type": "Polygon",
      "coordinates": [
        [
          [
            137.8952841144,
            34.704798870014
          ],
          [
            137.89527586017,
            34.705933194964
          ],
          [
            137.90178430521,
            34.705965321624
          ],
          [
            137.90179247062,
            34.704830995324
          ],
          [
            137.8952841144,
            34.704798870014
          ]
        ]
      ]
    }
  },
  "description": {
    "value": "平成30年度路面変状調査((一)403号線_磐田掛川線(下り)), ニチレキ(株)静岡支店"
  },
  "source": {
    "type": "URL",
    "value": "https://pointcloud.pref.shizuoka.jp"
  },
  "lasUrls": {
    "value": [
      "https://pointcloud.pref.shizuoka.jp/lasmap/public/30I8399017307/30I8399017307-1.las",
      "https://pointcloud.pref.shizuoka.jp/lasmap/public/30I8399017307/30I8399017307-2.las",
      "https://pointcloud.pref.shizuoka.jp/lasmap/public/30I8399017307/30I8399017307-3.las",
      "https://pointcloud.pref.shizuoka.jp/lasmap/public/30I8399017307/30I8399017307-4.las"
    ]
  },
  "lasSizes": {
    "value": [
      "200MB",
      "200MB",
      "200MB",
      "11MB"
    ]
  },
  "license": {
    "type": "URL",
    "value": "https://creativecommons.org/licenses/by/4.0/legalcode.ja"
  }
}