{
  "productNo": {
    "value": "30-I8399-01-04-04"
  },
  "name": {
    "value": "平成30年度路面変状調査((国)150号(下り)_(BP-9kp))"
  },
  "contractorName": {
    "value": "ニチレキ(株)静岡支店"
  },
  "constructionPeriod": {
    "value": ""
  },
  "registeredDate": {
    "value": "2019-10-15"
  },
  "measuredDate": {
    "value": "2019-03-31"
  },
  "sourceStatement": {
    "value": "出典：「静岡県ポイントクラウドデータベース」または「静岡県ＰＣＤＢ」"
  },
  "id": "shizuoka-pcd-30I8399010404",
  "type": "PointCloudDatabase",
  "location": {
    "type": "geo:json",
    "value": {
      "type": "Polygon",
      "coordinates": [
        [
          [
            138.15688301657,
            34.623611599975
          ],
          [
            138.15687807699,
            34.6248116222
          ],
          [
            138.16103594352,
            34.624823246934
          ],
          [
            138.16104082323,
            34.623623224191
          ],
          [
            138.15688301657,
            34.623611599975
          ]
        ]
      ]
    }
  },
  "description": {
    "value": "平成30年度路面変状調査((国)150号(下り)_(BP-9kp)), ニチレキ(株)静岡支店"
  },
  "source": {
    "type": "URL",
    "value": "https://pointcloud.pref.shizuoka.jp"
  },
  "lasUrls": {
    "value": [
      "https://pointcloud.pref.shizuoka.jp/lasmap/public/30I8399010404/30I8399010404-1.las",
      "https://pointcloud.pref.shizuoka.jp/lasmap/public/30I8399010404/30I8399010404-2.las",
      "https://pointcloud.pref.shizuoka.jp/lasmap/public/30I8399010404/30I8399010404-3.las"
    ]
  },
  "lasSizes": {
    "value": [
      "200MB",
      "200MB",
      "180MB"
    ]
  },
  "license": {
    "type": "URL",
    "value": "https://creativecommons.org/licenses/by/4.0/legalcode.ja"
  }
}